promptimus/__init__.py
promptimus/errors.py
promptimus/py.typed
promptimus/common/rate_limiting.py
promptimus/core/__init__.py
promptimus/core/checkpointing.py
promptimus/core/module.py
promptimus/core/parameters.py
promptimus/dto/__init__.py
promptimus/dto/image.py
promptimus/dto/message.py
promptimus/dto/tool.py
promptimus/embedders/__init__.py
promptimus/embedders/base.py
promptimus/embedders/openai.py
promptimus/embedders/ops.py
promptimus/llms/__init__.py
promptimus/llms/base.py
promptimus/llms/dummy.py
promptimus/llms/ollama.py
promptimus/llms/openai.py
promptimus/modules/__init__.py
promptimus/modules/memory.py
promptimus/modules/prompt.py
promptimus/modules/rag.py
promptimus/modules/retrieval.py
promptimus/modules/structural.py
promptimus/modules/tool.py
promptimus/vectore_store/__init__.py
promptimus/vectore_store/base.py
promptimus-0.1.11.dist-info/METADATA
promptimus-0.1.11.dist-info/WHEEL
promptimus-0.1.11.dist-info/licenses/LICENSE
promptimus-0.1.11.dist-info/RECORD
