Metadata-Version: 2.4
Name: promptimus
Version: 0.1.11
Summary: A PyTorch-like API for building composable LLM agents
Author-email: ailadin <korzhukandrew@gmail.com>
License-File: LICENSE
Requires-Python: >=3.12
Requires-Dist: loguru>=0.7.3
Requires-Dist: openai>=1.58.1
Requires-Dist: pydantic>=2.10.4
Requires-Dist: tomlkit>=0.13.2
Provides-Extra: chromadb
Requires-Dist: promptimus-chromadb-store; extra == 'chromadb'
Provides-Extra: phoenix
Requires-Dist: promptimus-phoenix-tracer; extra == 'phoenix'
Provides-Extra: testing
Requires-Dist: pytest-asyncio>=0.25.0; extra == 'testing'
Requires-Dist: pytest>=8.3.4; extra == 'testing'
